{
  "base": "semantic/",
  "theme": "tds",
  "paths": {
    "source": {
      "config": "src/theme.config",
      "definitions": "src/definitions/",
      "site": "src/site/",
      "themes": "src/themes/"
    },
    "output": {
      "packaged": "dist-tds/",
      "uncompressed": "dist-tds/components/",
      "compressed": "dist-tds/components/",
      "themes": "dist-tds/themes/"
    },
    "clean": "dist-tds/"
  },
  "permission": false,
  "autoInstall": false,
  "rtl": false,
  "version": "2.4.2"
}